airflow_sops/__init__.py
airflow_sops/helpers.py
airflow_sops/secrets_backend.py
airflow_sops_secrets_backend-0.0.2.dist-info/LICENSE.txt
airflow_sops_secrets_backend-0.0.2.dist-info/METADATA
airflow_sops_secrets_backend-0.0.2.dist-info/WHEEL
airflow_sops_secrets_backend-0.0.2.dist-info/top_level.txt
airflow_sops_secrets_backend-0.0.2.dist-info/RECORD
