Metadata-Version: 2.1
Name: airflow-sops-secrets-backend
Version: 0.0.2
Summary: A airflow_sops secrets backend with sops
Home-page: https://github.com/paulvitic/airflow-sops-secrets-backend
Author: Paul Vitic
Author-email: pvitic@comatch.com
Project-URL: Bug Reports, https://github.com/paulvitic/airflow-sops-secrets-backend/issues
Project-URL: Source, https://github.com/paulvitic/airflow-sops-secrets-backend
Keywords: airflow,sops,secrets-backend
Requires-Python: >=3.8, <4
License-File: LICENSE.txt
Requires-Dist: apache-airflow (>=2.2.3)
Requires-Dist: google-cloud-kms (>=2.10.1)
Requires-Dist: google-cloud-storage (>=1.43.0)
Requires-Dist: ruamel.yaml (>=0.17.21)
Requires-Dist: markupsafe (==2.0.1)
Provides-Extra: dev
Requires-Dist: setuptools (>=40.8.0) ; extra == 'dev'
Requires-Dist: build ; extra == 'dev'
Requires-Dist: twine ; extra == 'dev'
Requires-Dist: keyrings.google-artifactregistry-auth ; extra == 'dev'
Requires-Dist: wheel ; extra == 'dev'
Provides-Extra: test
Requires-Dist: python-dotenv ; extra == 'test'
Requires-Dist: pytest ; extra == 'test'
